ergon/main.py
ergon-0.1.0.dist-info/WHEEL
ergon-0.1.0.dist-info/METADATA
ergon-0.1.0.dist-info/RECORD
